Workbook

Sheet Overview
A1: FSK Codehouse Corp. — Service Pricing Structure
A4: Positioning
A5: Built from the Philippines, delivered to global standards. Rates sit above budget PH freelance work and template shops, and below premium US/EU agency pricing — reflecting senior, end-to-end delivery (strategy, design, engineering, launch, support) at PH-based cost efficiency.
A8: Reference exchange rate (USD → PHP) | B8: 61.75 | C8: As of Jul 22, 2026 (source: XE.com). Update this cell — all PHP prices recalculate automatically.
A10: How to use this workbook
A11: • Blue text on a yellow cell = an input you can edit (e.g. the exchange rate above).
A12: • Every PHP column is a formula off the USD price and the exchange rate — edit USD prices, PHP updates itself.
A13: • Each service line has its own tab with three tiers. Add-ons & retainers are on their own tab.
A14: • Market Benchmarks tab has the research this pricing is based on, with sources.
A17: Engagement Models
A18: Model | B18: How it's priced | C18: Best for
A19: Build for you | B19: Fixed project price by tier (see service tabs). 30–50% deposit, balance on milestones/delivery. | C19: Clients with a defined scope: a website, storefront, or app to launch.
A20: Build with you | B20: Reduced cash rate + equity, revenue share, or long-term retainer, negotiated per partnership. | C20: Strong founders/ideas where FSK becomes a technical co-builder.
A21: Built by FSK | B21: Not billed — internal investment in FSK-owned products (e.g. Lenso). | C21: Internal only. Not quoted to clients.

Sheet Real Estate Websites
A1: Real Estate Websites
A3: Property websites, searchable listings, agent pages, inquiry flows, and inventory tools.
A5: Tier | B5: USD Low | C5: USD High | D5: PHP Low | E5: PHP High | F5: Typical Timeline | G5: What's Included / Best For
A6: Starter | B6: 900 | C6: 1800 | D6: =B6*Overview!$B$8 -> 55575 | E6: =C6*Overview!$B$8 -> 111150 | F6: 2–3 weeks | G6: Template-based property site: 1 property type, static listings, contact/inquiry form, mobile-friendly. Best for a single agent testing an online presence.
A7: Growth (Semi-Custom) | B7: 2800 | C7: 7000 | D7: =B7*Overview!$B$8 -> 172900 | E7: =C7*Overview!$B$8 -> 432250 | F7: 4–8 weeks | G7: Semi-custom design, searchable/filterable listings, agent profile pages, lead-capture forms, basic CMS for updating inventory. Best for active agents or small teams.
A8: Custom Platform | B8: 9000 | C8: 25000 | D8: =B8*Overview!$B$8 -> 555750 | E8: =C8*Overview!$B$8 -> 1543750 | F8: 10–16 weeks | G8: Fully custom design and back-end, multi-agent/brokerage support, advanced search & filters, admin dashboard, integrations (CRM, IDX-equivalent feeds). Best for brokerages and growing portfolios.
A11: Common add-ons
A12: Add-on | B12: USD Low | C12: USD High
A13: Listing feed / IDX-equivalent integration | B13: 800 | C13: 3000
A14: Extra language / localization | B14: 400 | C14: 1200
A15: Property CRM integration | B15: 500 | C15: 2000

Sheet Digital Commerce
A1: Digital Commerce
A3: Storefronts for templates, downloads, memberships, and other digital goods.
A5: Tier | B5: USD Low | C5: USD High | D5: PHP Low | E5: PHP High | F5: Typical Timeline | G5: What's Included / Best For
A6: Starter Storefront | B6: 1200 | C6: 2800 | D6: =B6*Overview!$B$8 -> 74100 | E6: =C6*Overview!$B$8 -> 172900 | F6: 2–4 weeks | G6: Template-based store, single product line, payment processing, automated digital delivery. Best for a first digital product launch.
A7: Growth (Semi-Custom) | B7: 3800 | C7: 9000 | D7: =B7*Overview!$B$8 -> 234650 | E7: =C7*Overview!$B$8 -> 555750 | F7: 5–9 weeks | G7: Semi-custom storefront design, multiple product lines, membership/subscription support, upsell flows, basic analytics. Best for growing digital product businesses.
A8: Custom Commerce Platform | B8: 11000 | C8: 28000 | D8: =B8*Overview!$B$8 -> 679250 | E8: =C8*Overview!$B$8 -> 1729000 | F8: 10–18 weeks | G8: Fully custom storefront and checkout experience, multi-product catalog, membership tiers, custom admin tooling, third-party integrations (email, CRM, analytics). Best for established brands scaling digital sales.

Sheet Web & Mobile Apps
A1: Web & Mobile Apps
A3: Production-ready software for clients, co-build partnerships, and FSK-owned products.
A5: Tier | B5: USD Low | C5: USD High | D5: PHP Low | E5: PHP High | F5: Typical Timeline | G5: What's Included / Best For
A6: MVP | B6: 6000 | C6: 15000 | D6: =B6*Overview!$B$8 -> 370500 | E6: =C6*Overview!$B$8 -> 926250 | F6: 8–12 weeks | G6: Single-platform app (web or one mobile OS), core feature set only, ships fast to validate the idea with real users. Best for founders testing a concept.
A7: Mid-Complexity | B7: 16000 | C7: 40000 | D7: =B7*Overview!$B$8 -> 988000 | E7: =C7*Overview!$B$8 -> 2470000 | F7: 12–20 weeks | G7: Multi-platform (web + iOS/Android, or full-stack web app), custom backend, authentication, payments/subscriptions, admin tooling. Best for funded startups and established businesses.
A8: Full Product Build | B8: 40000 | C8: 90000 | D8: =B8*Overview!$B$8 -> 2470000 | E8: =C8*Overview!$B$8 -> 5557500 | F8: 20+ weeks | G8: Feature-rich, multi-platform product with ongoing iteration. Typically paired with a 'Build with you' partnership rather than a one-off fixed price.

Sheet Retainers & Add-ons
A1: Retainers & Add-ons
A3: Ongoing care plans after launch, billed monthly.
A5: Plan | B5: USD / month | C5: PHP / month | D5: Response Time | E5: What's Included
A6: Basic Care | B6: 150 | C6: =B6*Overview!$B$8 -> 9262.5 | D6: 2 business days | E6: Uptime monitoring, security patches, bug fixes, monthly health-check email.
A7: Growth Care | B7: 350 | C7: =B7*Overview!$B$8 -> 21612.5 | D7: 1 business day | E7: Everything in Basic, plus minor feature updates (up to 4 hrs/mo), monthly performance report.
A8: Priority Care | B8: 600 | C8: =B8*Overview!$B$8 -> 37050 | D8: Same business day | E8: Everything in Growth, plus dedicated Slack/chat channel, priority queue for urgent fixes, up to 10 hrs/mo of feature work.
A10: One-off add-ons
A11: Add-on | B11: USD Low | C11: USD High | D11: Notes
A12: SEO retainer (separate from Care plans) | B12: 400 | C12: 2500 | D12: Monthly; scope depends on keyword competitiveness.
A13: App Store / Play Store submission & setup | B13: 300 | C13: 800 | D13: Per platform, one-time.
A14: Extra design round beyond agreed revisions | B14: 300 | C14: 1500 | D14: Billed per round.
A15: Rush delivery (compressed timeline) | B15: +20% | C15: +40% | D15: Applied on top of tier price.

Sheet Market Benchmarks
A1: Market Benchmarks (Research, Jul 2026)
A4: Category | B4: Benchmark Range Found | C4: Source | D4: Notes
A5: Real estate website (global, agent) | B5: $2,000 – $45,000+; typical $4,000–$12,000 for solo agents | C5: Symilars, Luxury Presence | D5: FSK Starter/Growth tiers sit near or below the low-mid end of this range.
A6: Real estate website (team/brokerage) | B6: $12,000 – $30,000 | C6: Luxury Presence | D6: FSK Custom Platform tier is positioned inside this band.
A7: IDX / listing feed integration | B7: $1,500 – $5,000 | C7: Luxury Presence | D7: FSK add-on priced below this to stay competitive as a PH-based provider.
A8: Ecommerce website (template) | B8: $1,000 – $5,000 | C8: Shopify, BigCommerce | D8: FSK Starter Storefront undercuts the low end slightly.
A9: Ecommerce website (semi-custom) | B9: $10,000 – $30,000 | C9: Shopify, BigCommerce | D9: FSK Growth tier sits below this band.
A10: Ecommerce website (fully custom) | B10: $40,000 – $150,000+ | C10: Shopify, BigCommerce, Fyresite | D10: FSK Custom Commerce priced well under this — reflects PH cost base.
A11: Mobile/web app (simple) | B11: $10,000 – $50,000 (global agencies) | C11: TopFlight Apps, Cynoteck | D11: FSK MVP tier priced at the low end, reflecting leaner PH-based delivery.
A12: Mobile/web app (mid-complexity) | B12: $30,000 – $150,000 | C12: TopFlight Apps, SSNTPL | D12: FSK Mid-Complexity tier priced toward the lower half.
A13: Hourly dev rates (global) | B13: Junior $25–45/hr, Mid $50–90/hr, Senior $100–200/hr | C13: Cynoteck, Topflightapps | D13: For reference only — FSK quotes fixed project prices, not hourly.
A14: PH web/software dev market | B14: Simple sites ₱12k–45k (~$200–750); custom ₱200k–1M+ ($3,200–$16,000+); PH dev hourly $20–55/hr | C14: Hireplicity, Qadra Studio, Praferosa Webworks | D14: FSK prices above pure local-market rates to reflect 'global standards' positioning, but below premium US/EU agencies.
A16: Research conducted via live web search, July 22, 2026. Figures are directional market ranges, not quotes — confirm current rates before publishing final prices.
